setup.cfg
setup.py
Flask_B1Connector.egg-info/PKG-INFO
Flask_B1Connector.egg-info/SOURCES.txt
Flask_B1Connector.egg-info/dependency_links.txt
Flask_B1Connector.egg-info/not-zip-safe
Flask_B1Connector.egg-info/requires.txt
Flask_B1Connector.egg-info/top_level.txt
flask_b1connector/__init__.py
flask_b1connector/flask_b1connector.py